CHANGELOG.txt
LICENCE.txt
MANIFEST.in
README.txt
requirements.txt
setup.py
kiqnetworktools/__init__.py
kiqnetworktools.egg-info/PKG-INFO
kiqnetworktools.egg-info/SOURCES.txt
kiqnetworktools.egg-info/dependency_links.txt
kiqnetworktools.egg-info/requires.txt
kiqnetworktools.egg-info/top_level.txt