Metadata-Version: 2.1
Name: kiqnetworktools
Version: 0.0.3
Summary: Tools for Networking
Home-page: UNKNOWN
Author: Luis Cueva
Author-email: lecuevad@gmail.com
License: MIT
Keywords: kiqnetworktools
Platform: UNKNOWN
Classifier: Development Status :: 5 - Production/Stable
Classifier: Intended Audience :: Education
Classifier: Operating System :: Microsoft :: Windows :: Windows 10
Classifier: License :: OSI Approved :: MIT License
Classifier: Programming Language :: Python :: 3
